iso18245/__init__.py
iso18245/data/alipay_list.csv
iso18245/data/amex_list.csv
iso18245/data/iso18245_official_list.csv
iso18245/data/iso18245_ranges.csv
iso18245/data/mastercard_list.csv
iso18245/data/private_ranges.csv
iso18245/data/stripe_list.csv
iso18245/data/usda_list.csv
iso18245/data/visa_list.csv
iso18245/py.typed
iso18245-1.4.1.dist-info/LICENSE
iso18245-1.4.1.dist-info/METADATA
iso18245-1.4.1.dist-info/WHEEL
iso18245-1.4.1.dist-info/RECORD
