Metadata-Version: 2.3
Name: iso18245
Version: 1.4.1
Summary: The ISO 18245 Merchant Category Codes database
License: MIT
Author: Jerome Leclanche
Author-email: jerome@leclan.ch
Requires-Python: >=3.8,<4.0
Classifier: Development Status :: 5 - Production/Stable
Classifier: Intended Audience :: Developers
Classifier: License :: OSI Approved :: MIT License
Classifier: Programming Language :: Python :: 3
Classifier: Programming Language :: Python :: 3.8
Classifier: Programming Language :: Python :: 3.9
Classifier: Programming Language :: Python :: 3.10
Classifier: Programming Language :: Python :: 3.11
Classifier: Programming Language :: Python :: 3.12
Classifier: Programming Language :: Python :: 3.13
Classifier: Topic :: Office/Business :: Financial
Classifier: Topic :: Office/Business :: Financial :: Accounting
Classifier: Topic :: Software Development :: Libraries :: Python Modules
Requires-Dist: importlib_resources (>=5.4.0,<6.0.0)
Project-URL: Repository, https://github.com/jleclanche/python-iso18245
